{
  "sections": {
    "main": {
      "type": "main-page",
      "disabled": true,
      "settings": {
      }
    },
    "rich_text_jnBDC4": {
      "type": "rich-text",
      "blocks": {
        "text_7hHbVY": {
          "type": "text",
          "settings": {
            "text": "<p>Culture at ShopTrade<\/p>",
            "text_font": "text-font--headings",
            "text_size": "text-size--100",
            "mobile_text_size": "1",
            "text_line_height": "text-line-height--default",
            "seo_h_tag": "span"
          }
        },
        "text_8TrKNQ": {
          "type": "text",
          "settings": {
            "text": "<p>Scale your business with a team of highly skilled professionals<\/p>",
            "text_font": "text-font--body",
            "text_size": "text-size--20",
            "mobile_text_size": "1",
            "text_line_height": "text-line-height--default",
            "seo_h_tag": "span"
          }
        },
        "button_xEdW47": {
          "type": "button",
          "disabled": true,
          "settings": {
            "button_label": "Contact Us",
            "link": "",
            "target": false,
            "button_style": "solid",
            "button_size": "button--regular",
            "button_hover": "-arrow"
          }
        }
      },
      "block_order": [
        "text_7hHbVY",
        "text_8TrKNQ",
        "button_xEdW47"
      ],
      "settings": {
        "heading": "",
        "seo_h_tag": "h2",
        "disable_section_title_border": false,
        "image": "shopify:\/\/shop_images\/5K8A6607.jpg",
        "image_aspect_ratio": "1.33333",
        "image_position": "top no-image",
        "image_position_mobile": "above",
        "image_crop": false,
        "image_overlap": false,
        "image_overlay": "rgba(0,0,0,0)",
        "media_shape": "none",
        "remove_media_border_radius": false,
        "text_alignment": "horizontal-left align-content--vertical-middle",
        "spacing": 24,
        "gutter": "grid-padding",
        "width": "70",
        "color_scheme": "",
        "disable_section_bottom_border": false,
        "color_scheme_card": "",
        "disable_border": true,
        "remove_border_radius": false,
        "remove_padding": true,
        "add_border": true,
        "hide_block_if": false
      }
    },
    "image_xQfN9c": {
      "type": "image",
      "settings": {
        "heading": "",
        "seo_h_tag": "h2",
        "disable_section_title_border": false,
        "image": "shopify:\/\/shop_images\/5K8A6607.jpg",
        "media_shape": "none",
        "link": "",
        "open_in_new_window": false,
        "color_scheme": "",
        "disable_section_bottom_border": false,
        "remove_border_radius": false,
        "remove_padding": false,
        "hide_block_if": false
      }
    },
    "promotion_blocks_mLNkjm": {
      "type": "promotion-blocks",
      "blocks": {
        "card_jWGCWd": {
          "type": "card",
          "settings": {
            "image_overlay": "rgba(0,0,0,0)",
            "image_overlay_opacity": 30,
            "media_shape": "none",
            "add_gallery_item_border": false,
            "hide_media": true,
            "title": "Our Mission",
            "subtitle": "Our mission is to establish a network of entrepreneurs that help each other with the sole purpose of scaling their businesses. In an ever-changing online world, the only way to stay ahead of the curve is by surrounding yourself with like-minded energetic professionals.",
            "text_color_scheme": "",
            "button_label": "",
            "button_link": "",
            "target": false,
            "seo_h_tag": "h3"
          }
        },
        "card_A4nmhN": {
          "type": "card",
          "settings": {
            "image_overlay": "rgba(0,0,0,0)",
            "image_overlay_opacity": 30,
            "media_shape": "none",
            "add_gallery_item_border": false,
            "hide_media": true,
            "title": "Our Vision",
            "subtitle": "Our vision is to become the swiss army knife that every online entrepreneur has in their pockets. We’re getting there through intelligent partnerships with established companies, building our own suite of products, and enabling clients to reach new business heights by providing them with on-demand teams of agile professionals.",
            "text_color_scheme": "",
            "button_label": "",
            "button_link": "",
            "target": false,
            "seo_h_tag": "h3"
          }
        }
      },
      "block_order": [
        "card_jWGCWd",
        "card_A4nmhN"
      ],
      "settings": {
        "heading": "",
        "seo_h_tag": "h2",
        "disable_section_title_border": false,
        "layout_desktop": "grid-2",
        "layout_mobile": "grid-palm-1",
        "style": "grid",
        "image_aspect_ratio": "2",
        "alignment": "horizontal-left align-content--vertical-top",
        "width": "70",
        "title_font": "text-font--headings",
        "title_size": "text-size--80",
        "mobile_text_size": "1",
        "subtitle_size": "text-size--18",
        "spacing": 12,
        "gutter": "grid-padding",
        "button_style": "outline",
        "button_size": "button--regular",
        "button_hover": "-arrow",
        "cta_label": "",
        "cta_url": "",
        "color_scheme": "scheme1",
        "disable_section_bottom_border": false,
        "disable_border": false,
        "remove_border_radius": false,
        "remove_padding": false,
        "hide_block_if": false
      }
    },
    "vertical_slider_BxeYTt": {
      "type": "vertical-slider",
      "blocks": {
        "slide_dhnwEM": {
          "type": "slide",
          "settings": {
            "image": "shopify:\/\/shop_images\/5K8A6537.jpg",
            "image_overlay": "rgba(0,0,0,0)",
            "image_overlay_opacity": 30,
            "hide_media": false,
            "title": "",
            "subtitle": "",
            "text_color_scheme": "scheme2",
            "text_blending": "normal",
            "button_label": "",
            "button_link": "",
            "target": false,
            "seo_h_tag_title": "h2",
            "seo_h_tag_subtitle": "span"
          }
        },
        "slide_ir8pwC": {
          "type": "slide",
          "settings": {
            "image": "shopify:\/\/shop_images\/5K8A6568.jpg",
            "image_overlay": "rgba(0,0,0,0)",
            "image_overlay_opacity": 30,
            "hide_media": false,
            "title": "",
            "subtitle": "",
            "text_color_scheme": "scheme2",
            "text_blending": "normal",
            "button_label": "",
            "button_link": "",
            "target": false,
            "seo_h_tag_title": "h2",
            "seo_h_tag_subtitle": "span"
          }
        },
        "slide_6xRNPz": {
          "type": "slide",
          "settings": {
            "image": "shopify:\/\/shop_images\/5K8A6475.jpg",
            "image_overlay": "rgba(0,0,0,0)",
            "image_overlay_opacity": 30,
            "hide_media": false,
            "title": "",
            "subtitle": "",
            "text_color_scheme": "scheme2",
            "text_blending": "normal",
            "button_label": "",
            "button_link": "",
            "target": false,
            "seo_h_tag_title": "h2",
            "seo_h_tag_subtitle": "span"
          }
        },
        "slide_JHUYfP": {
          "type": "slide",
          "settings": {
            "image": "shopify:\/\/shop_images\/5K8A6461.jpg",
            "image_overlay": "rgba(0,0,0,0)",
            "image_overlay_opacity": 30,
            "hide_media": false,
            "title": "",
            "subtitle": "",
            "text_color_scheme": "scheme2",
            "text_blending": "normal",
            "button_label": "",
            "button_link": "",
            "target": false,
            "seo_h_tag_title": "h2",
            "seo_h_tag_subtitle": "span"
          }
        }
      },
      "block_order": [
        "slide_dhnwEM",
        "slide_ir8pwC",
        "slide_6xRNPz",
        "slide_JHUYfP"
      ],
      "settings": {
        "image_aspect_ratio_desktop": "1.77777",
        "image_aspect_ratio_mobile": "1",
        "media_shape": "none",
        "add_gallery_item_border": false,
        "alignment": "horizontal-left align-content--vertical-top",
        "width": "100",
        "spacing": 12,
        "gutter": "grid-padding",
        "title_text_font": "text-font--headings",
        "title_text_size": "text-size--60",
        "title_mobile_size": "1",
        "title_text_line_height": "text-line-height--default",
        "subtitle_text_font": "text-font--body",
        "subtitle_text_size": "text-size--20",
        "subtitle_mobile_size": "1",
        "subtitle_text_line_height": "text-line-height--default",
        "button_style": "outline",
        "button_size": "button--regular",
        "button_hover": "-arrow",
        "color_scheme": "scheme3",
        "disable_section_bottom_border": false,
        "remove_border_radius": false,
        "remove_padding": false,
        "remove_zoom": false,
        "remove_prlx": false
      }
    },
    "promotion_blocks_jTkEbT": {
      "type": "promotion-blocks",
      "blocks": {
        "card_rKyzdR": {
          "type": "card",
          "settings": {
            "image_overlay": "rgba(0,0,0,0)",
            "image_overlay_opacity": 30,
            "media_shape": "none",
            "add_gallery_item_border": false,
            "hide_media": true,
            "title": "5+ Years",
            "subtitle": "We’re young, but with 5+ years' worth of domain experience, we’re here to help you get to the next stage.",
            "text_color_scheme": "",
            "button_label": "",
            "button_link": "",
            "target": false,
            "seo_h_tag": "h3"
          }
        },
        "card_iHffHN": {
          "type": "card",
          "settings": {
            "image_overlay": "rgba(0,0,0,0)",
            "image_overlay_opacity": 30,
            "media_shape": "none",
            "add_gallery_item_border": false,
            "hide_media": true,
            "title": "100% Success",
            "subtitle": "It’s not always easy, but no matter what, we deliver. It’s our mission to go above and beyond for our clients.",
            "text_color_scheme": "",
            "button_label": "",
            "button_link": "",
            "target": false,
            "seo_h_tag": "h3"
          }
        },
        "card_bBkpQ6": {
          "type": "card",
          "settings": {
            "image_overlay": "rgba(0,0,0,0)",
            "image_overlay_opacity": 30,
            "media_shape": "none",
            "add_gallery_item_border": false,
            "hide_media": true,
            "title": "200+ Projects",
            "subtitle": "Successfully delivered 200+ projects so far. Always on the lookout for the next one.",
            "text_color_scheme": "",
            "button_label": "",
            "button_link": "",
            "target": false,
            "seo_h_tag": "h3"
          }
        },
        "card_8wMnnC": {
          "type": "card",
          "settings": {
            "image_overlay": "rgba(0,0,0,0)",
            "image_overlay_opacity": 30,
            "media_shape": "none",
            "add_gallery_item_border": false,
            "hide_media": true,
            "title": "95% Retention",
            "subtitle": "We're treating every client as the first one. That's why most of them stick with us.",
            "text_color_scheme": "",
            "button_label": "",
            "button_link": "",
            "target": false,
            "seo_h_tag": "h3"
          }
        }
      },
      "block_order": [
        "card_rKyzdR",
        "card_iHffHN",
        "card_bBkpQ6",
        "card_8wMnnC"
      ],
      "settings": {
        "heading": "Our Numbers",
        "seo_h_tag": "h2",
        "disable_section_title_border": false,
        "layout_desktop": "grid-4 grid-lap-3",
        "layout_mobile": "grid-palm-1",
        "style": "grid",
        "image_aspect_ratio": "1",
        "alignment": "horizontal-left align-content--vertical-middle",
        "width": "100",
        "title_font": "text-font--headings",
        "title_size": "text-size--80",
        "mobile_text_size": "1",
        "subtitle_size": "text-size--18",
        "spacing": 12,
        "gutter": "grid-padding",
        "button_style": "outline",
        "button_size": "button--regular",
        "button_hover": "-arrow",
        "cta_label": "",
        "cta_url": "",
        "color_scheme": "scheme1",
        "disable_section_bottom_border": false,
        "disable_border": false,
        "remove_border_radius": false,
        "remove_padding": false,
        "hide_block_if": false
      }
    },
    "video_Mx63EX": {
      "type": "video",
      "settings": {
        "heading": "Our Values",
        "seo_h_tag": "h2",
        "disable_section_title_border": false,
        "video": "https:\/\/www.youtube.com\/watch?v=_9VUPq3SxOc",
        "add_border": true,
        "border_color": "#000000",
        "video_height": 56,
        "image": "shopify:\/\/shop_images\/5K8A6537.jpg",
        "color_scheme": "scheme4",
        "disable_section_bottom_border": false,
        "remove_border_radius": false,
        "remove_padding": false
      }
    },
    "promotion_blocks_RcyXUR": {
      "type": "promotion-blocks",
      "blocks": {
        "card_CBiFy7": {
          "type": "card",
          "settings": {
            "image_overlay": "rgba(0,0,0,0)",
            "image_overlay_opacity": 30,
            "media_shape": "none",
            "add_gallery_item_border": false,
            "hide_media": true,
            "title": "Personal Touch",
            "subtitle": "Each of our customers ranks first on our priority list. We’re constantly seeking ways to make your life easier. We treat each project as our own, and we get heavily invested in your product, no matter whether you’re a start-up, mid-sized, or enterprise-level company.",
            "text_color_scheme": "",
            "button_label": "",
            "button_link": "",
            "target": false,
            "seo_h_tag": "h3"
          }
        },
        "card_By3pUd": {
          "type": "card",
          "settings": {
            "image_overlay": "rgba(0,0,0,0)",
            "image_overlay_opacity": 30,
            "media_shape": "none",
            "add_gallery_item_border": false,
            "hide_media": true,
            "title": "Transparency",
            "subtitle": "Transparency is the foundation of successful long-term collaborations, and we love those. When working with ShopTrade, you’ll embark on a journey of growth while our team of professionals will guide you every step of the way.",
            "text_color_scheme": "",
            "button_label": "",
            "button_link": "",
            "target": false,
            "seo_h_tag": "h3"
          }
        },
        "card_PVTHxG": {
          "type": "card",
          "settings": {
            "image_overlay": "rgba(0,0,0,0)",
            "image_overlay_opacity": 30,
            "media_shape": "none",
            "add_gallery_item_border": false,
            "hide_media": true,
            "title": "Passion",
            "subtitle": "We surround ourselves only with passionate people because we believe in win-win relationships where our clients are delighted with successful products that take their customer base and conversion to a new level.",
            "text_color_scheme": "",
            "button_label": "",
            "button_link": "",
            "target": false,
            "seo_h_tag": "h3"
          }
        },
        "card_mnQKp7": {
          "type": "card",
          "settings": {
            "image_overlay": "rgba(0,0,0,0)",
            "image_overlay_opacity": 30,
            "media_shape": "none",
            "add_gallery_item_border": false,
            "hide_media": true,
            "title": "Quality",
            "subtitle": "Our priority is delivering highly scalable pixel-perfect solutions. We’re not here to jump from one project to the other but rather to help our clients becoming established brands in their market, and the only way to do so is with high-quality services.",
            "text_color_scheme": "",
            "button_label": "",
            "button_link": "",
            "target": false,
            "seo_h_tag": "h3"
          }
        }
      },
      "block_order": [
        "card_CBiFy7",
        "card_By3pUd",
        "card_PVTHxG",
        "card_mnQKp7"
      ],
      "settings": {
        "heading": "",
        "seo_h_tag": "h2",
        "disable_section_title_border": false,
        "layout_desktop": "grid-2",
        "layout_mobile": "grid-palm-1",
        "style": "grid",
        "image_aspect_ratio": "2",
        "alignment": "horizontal-left align-content--vertical-top",
        "width": "70",
        "title_font": "text-font--headings",
        "title_size": "text-size--80",
        "mobile_text_size": "1",
        "subtitle_size": "text-size--18",
        "spacing": 12,
        "gutter": "grid-padding",
        "button_style": "outline",
        "button_size": "button--regular",
        "button_hover": "-arrow",
        "cta_label": "",
        "cta_url": "",
        "color_scheme": "scheme4",
        "disable_section_bottom_border": false,
        "disable_border": false,
        "remove_border_radius": false,
        "remove_padding": false,
        "hide_block_if": false
      }
    },
    "promotion_blocks_HCAVU9": {
      "type": "promotion-blocks",
      "blocks": {
        "card_8DWgGw": {
          "type": "card",
          "settings": {
            "image": "shopify:\/\/shop_images\/Mifras_17d7bafe-3940-4fc8-9224-770f45e902f2.jpg",
            "image_overlay": "rgba(0,0,0,0)",
            "image_overlay_opacity": 30,
            "media_shape": "none",
            "add_gallery_item_border": true,
            "hide_media": false,
            "title": "",
            "subtitle": "",
            "text_color_scheme": "",
            "button_label": "",
            "button_link": "",
            "target": false,
            "seo_h_tag": "h3"
          }
        },
        "card_K3r7Ke": {
          "type": "card",
          "settings": {
            "image_overlay": "rgba(0,0,0,0)",
            "image_overlay_opacity": 30,
            "media_shape": "none",
            "add_gallery_item_border": false,
            "hide_media": true,
            "title": "Mohammadu Mifras",
            "subtitle": "FOUNDER & CEO\n\nMifras is a young entrepreneur with a deep understanding of Commerce solutions and a proven track record of scaling online businesses, working with companies looking to transition to, or expand, their online presence.   He has successfully built, developed and launched a significant number of DTC brands for his clients.",
            "text_color_scheme": "",
            "button_label": "",
            "button_link": "",
            "target": false,
            "seo_h_tag": "h3"
          }
        },
        "card_pViLtP": {
          "type": "card",
          "settings": {
            "image": "shopify:\/\/shop_images\/Deekshith.jpg",
            "image_overlay": "rgba(0,0,0,0)",
            "image_overlay_opacity": 30,
            "media_shape": "none",
            "add_gallery_item_border": true,
            "hide_media": false,
            "title": "",
            "subtitle": "",
            "text_color_scheme": "",
            "button_label": "",
            "button_link": "",
            "target": false,
            "seo_h_tag": "h3"
          }
        },
        "card_f3xNbW": {
          "type": "card",
          "settings": {
            "image_overlay": "rgba(0,0,0,0)",
            "image_overlay_opacity": 30,
            "media_shape": "none",
            "add_gallery_item_border": false,
            "hide_media": true,
            "title": "Deekshith K Suvarna",
            "subtitle": "DIRECTOR (INDIA) | HEAD OF DESIGN\n\nDeekshith is an accomplished professional with over 9+ years of experience in the field of Design,  Branding, Graphic Design, UX, UI and Art Direction across various industries including Information Technology, Fashion, Food and Beverages. He believes that technology can revolutionise how people learn, communicate and create and he is passionate about shaping products and services that help people focus on what they do best.",
            "text_color_scheme": "scheme_1",
            "button_label": "",
            "button_link": "",
            "target": false,
            "seo_h_tag": "h3"
          }
        }
      },
      "block_order": [
        "card_8DWgGw",
        "card_K3r7Ke",
        "card_pViLtP",
        "card_f3xNbW"
      ],
      "settings": {
        "heading": "Say hello to the leaders",
        "seo_h_tag": "h2",
        "disable_section_title_border": false,
        "layout_desktop": "grid-4 grid-lap-3",
        "layout_mobile": "grid-palm-1",
        "style": "grid",
        "image_aspect_ratio": "1",
        "alignment": "horizontal-left align-content--vertical-top",
        "width": "100",
        "title_font": "text-font--headings",
        "title_size": "text-size--60",
        "mobile_text_size": "1",
        "subtitle_size": "text-size--18",
        "spacing": 12,
        "gutter": "grid-padding",
        "button_style": "outline",
        "button_size": "button--regular",
        "button_hover": "-arrow",
        "cta_label": "",
        "cta_url": "",
        "color_scheme": "scheme1",
        "disable_section_bottom_border": false,
        "disable_border": false,
        "remove_border_radius": false,
        "remove_padding": false,
        "hide_block_if": false
      }
    },
    "text_columns_images_Na86Er": {
      "type": "text-columns-images",
      "blocks": {
        "image_KxfFDM": {
          "type": "image",
          "disabled": true,
          "settings": {
            "image": "shopify:\/\/shop_images\/career-profile.png",
            "media_shape": "none",
            "title": "View Openings",
            "caption": "",
            "cta_label": "",
            "cta_url": "",
            "target": false,
            "seo_h_tag": "h3"
          }
        },
        "image_mCVe99": {
          "type": "image",
          "settings": {
            "image": "shopify:\/\/shop_images\/Amit_a1983923-7187-48d3-b3ee-0f2cf9e5132b.jpg",
            "media_shape": "none",
            "title": "Amit Gupta",
            "caption": "<p>Head of Engineering<\/p>",
            "cta_label": "",
            "cta_url": "",
            "target": false,
            "seo_h_tag": "h3"
          }
        },
        "image_dK63rr": {
          "type": "image",
          "settings": {
            "image": "shopify:\/\/shop_images\/Akila.jpg",
            "media_shape": "none",
            "title": "Akila Mohan",
            "caption": "<p>Senior Manager - People Operations<\/p>",
            "cta_label": "",
            "cta_url": "",
            "target": false,
            "seo_h_tag": "h3"
          }
        },
        "image_pbe3PX": {
          "type": "image",
          "settings": {
            "image": "shopify:\/\/shop_images\/Sushanth.jpg",
            "media_shape": "none",
            "title": "Sushanth Suvarna",
            "caption": "<p>Admin & HR Associate<\/p>",
            "cta_label": "",
            "cta_url": "",
            "target": false,
            "seo_h_tag": "h3"
          }
        },
        "image_fcebUT": {
          "type": "image",
          "settings": {
            "image": "shopify:\/\/shop_images\/Arjun.jpg",
            "media_shape": "none",
            "title": "Arjun GM",
            "caption": "<p>Business Analyst<\/p>",
            "cta_label": "",
            "cta_url": "",
            "target": false,
            "seo_h_tag": "h3"
          }
        },
        "image_9TGVBq": {
          "type": "image",
          "settings": {
            "image": "shopify:\/\/shop_images\/default_profile_1.jpg",
            "media_shape": "none",
            "title": "Vithika",
            "caption": "<p>Business Development Executive<\/p>",
            "cta_label": "",
            "cta_url": "",
            "target": false,
            "seo_h_tag": "h3"
          }
        },
        "image_Ab8Eix": {
          "type": "image",
          "settings": {
            "image": "shopify:\/\/shop_images\/Chaman.jpg",
            "media_shape": "none",
            "title": "Chaman Madhu",
            "caption": "<p>Design II - (Product Design Specialist)<\/p>",
            "cta_label": "",
            "cta_url": "",
            "target": false,
            "seo_h_tag": "h3"
          }
        },
        "image_Jii8PU": {
          "type": "image",
          "settings": {
            "image": "shopify:\/\/shop_images\/Faizal.jpg",
            "media_shape": "none",
            "title": "Faizal Ahmed",
            "caption": "<p>Design II - (Product Design Specialist)<\/p>",
            "cta_label": "",
            "cta_url": "",
            "target": false,
            "seo_h_tag": "h3"
          }
        },
        "image_rJtbdm": {
          "type": "image",
          "settings": {
            "image": "shopify:\/\/shop_images\/Rosh_54915d4c-6020-4e24-a339-9613d27bae6a.jpg",
            "media_shape": "none",
            "title": "Rosh VR",
            "caption": "<p>Design II - (User Interface Design Specialist)<\/p>",
            "cta_label": "",
            "cta_url": "",
            "target": false,
            "seo_h_tag": "h3"
          }
        },
        "image_A4YNrX": {
          "type": "image",
          "settings": {
            "image": "shopify:\/\/shop_images\/ash_2.png",
            "media_shape": "none",
            "title": "Adarsh S",
            "caption": "<p>Design II - (Multimedia Design Specialist)<\/p>",
            "cta_label": "",
            "cta_url": "",
            "target": false,
            "seo_h_tag": "h3"
          }
        },
        "image_T3Ecmy": {
          "type": "image",
          "settings": {
            "image": "shopify:\/\/shop_images\/default_profile_6.jpg",
            "media_shape": "none",
            "title": "Danish",
            "caption": "<p>Design II - (Visual Design Specialist)<\/p>",
            "cta_label": "",
            "cta_url": "",
            "target": false,
            "seo_h_tag": "h3"
          }
        },
        "image_ReqXVk": {
          "type": "image",
          "settings": {
            "image": "shopify:\/\/shop_images\/Pradeep_431e0921-d376-42a5-86f9-cb5e6012ed3e.jpg",
            "media_shape": "none",
            "title": "Pradeep Neginhal",
            "caption": "<p>Senior Front-End Engineering Manager<\/p>",
            "cta_label": "",
            "cta_url": "",
            "target": false,
            "seo_h_tag": "h3"
          }
        },
        "image_zLHitx": {
          "type": "image",
          "settings": {
            "image": "shopify:\/\/shop_images\/default_profile_2.jpg",
            "media_shape": "none",
            "title": "Umesh",
            "caption": "<p>Team Lead (Front-End)<\/p>",
            "cta_label": "",
            "cta_url": "",
            "target": false,
            "seo_h_tag": "h3"
          }
        },
        "image_TccPRx": {
          "type": "image",
          "settings": {
            "image": "shopify:\/\/shop_images\/default_profile_3.jpg",
            "media_shape": "none",
            "title": "Kaustubh",
            "caption": "<p>Head Of Theme<\/p>",
            "cta_label": "",
            "cta_url": "",
            "target": false,
            "seo_h_tag": "h3"
          }
        },
        "image_awrwUD": {
          "type": "image",
          "settings": {
            "image": "shopify:\/\/shop_images\/Sumayya.jpg",
            "media_shape": "none",
            "title": "Sumayya Ishaq",
            "caption": "<p>Front-End Engineer<\/p>",
            "cta_label": "",
            "cta_url": "",
            "target": false,
            "seo_h_tag": "h3"
          }
        },
        "image_GWnRe7": {
          "type": "image",
          "settings": {
            "image": "shopify:\/\/shop_images\/Shivanshi.jpg",
            "media_shape": "none",
            "title": "Shivanshi Gupta",
            "caption": "<p>Front-End Engineer<\/p>",
            "cta_label": "",
            "cta_url": "",
            "target": false,
            "seo_h_tag": "h3"
          }
        },
        "image_giECXa": {
          "type": "image",
          "settings": {
            "image": "shopify:\/\/shop_images\/Darshika_70c19156-2db9-45ff-b68e-8f290eaea9b9.jpg",
            "media_shape": "none",
            "title": "Darshika Pillai",
            "caption": "<p>Front-End Engineer<\/p>",
            "cta_label": "",
            "cta_url": "",
            "target": false,
            "seo_h_tag": "h3"
          }
        },
        "image_kFAFMG": {
          "type": "image",
          "settings": {
            "image": "shopify:\/\/shop_images\/Keerthi.jpg",
            "media_shape": "none",
            "title": "Keerthi Sindhura",
            "caption": "<p>Front-End Engineer<\/p>",
            "cta_label": "",
            "cta_url": "",
            "target": false,
            "seo_h_tag": "h3"
          }
        },
        "image_DG73Cy": {
          "type": "image",
          "settings": {
            "image": "shopify:\/\/shop_images\/Sarudh.jpg",
            "media_shape": "none",
            "title": "Sahrudh Prathi",
            "caption": "<p>Front-End Engineer<\/p>",
            "cta_label": "",
            "cta_url": "",
            "target": false,
            "seo_h_tag": "h3"
          }
        },
        "image_8LDRXm": {
          "type": "image",
          "settings": {
            "image": "shopify:\/\/shop_images\/Vinod_30c4a7cf-fa58-43b7-941f-9b407a8cf4c7.jpg",
            "media_shape": "none",
            "title": "Vinod Kalyan",
            "caption": "<p>Front-End Engineer<\/p>",
            "cta_label": "",
            "cta_url": "",
            "target": false,
            "seo_h_tag": "h3"
          }
        },
        "image_gLMdt3": {
          "type": "image",
          "settings": {
            "image": "shopify:\/\/shop_images\/default_profile_4.jpg",
            "media_shape": "none",
            "title": "Madhan S",
            "caption": "<p>Software Developer Engineer-II<\/p>",
            "cta_label": "",
            "cta_url": "",
            "target": false,
            "seo_h_tag": "h3"
          }
        },
        "image_hBnaiL": {
          "type": "image",
          "settings": {
            "image": "shopify:\/\/shop_images\/default_profile_5.jpg",
            "media_shape": "none",
            "title": "Kenneth",
            "caption": "<p>Software Developer Engineer-II<\/p>",
            "cta_label": "",
            "cta_url": "",
            "target": false,
            "seo_h_tag": "h3"
          }
        },
        "image_JGFAa7": {
          "type": "image",
          "settings": {
            "image": "shopify:\/\/shop_images\/Nagavasavi.jpg",
            "media_shape": "none",
            "title": "Nagavasavi L",
            "caption": "<p>Quality Assurance Engineer<\/p>",
            "cta_label": "",
            "cta_url": "",
            "target": false,
            "seo_h_tag": "h3"
          }
        },
        "image_qbbcVw": {
          "type": "image",
          "settings": {
            "image": "shopify:\/\/shop_images\/Hadhil.jpg",
            "media_shape": "none",
            "title": "Mohamed Hadhil",
            "caption": "<p>Support Engineer<\/p>",
            "cta_label": "",
            "cta_url": "",
            "target": false,
            "seo_h_tag": "h3"
          }
        },
        "image_h94zNC": {
          "type": "image",
          "settings": {
            "image": "shopify:\/\/shop_images\/Shiv.jpg",
            "media_shape": "none",
            "title": "Shivanand A Khot",
            "caption": "<p>Front-End Engineer<\/p>",
            "cta_label": "",
            "cta_url": "",
            "target": false,
            "seo_h_tag": "h3"
          }
        },
        "image_7mHEQe": {
          "type": "image",
          "settings": {
            "image": "shopify:\/\/shop_images\/Ritu_86df88eb-cebc-4375-8672-908e67bc02bb.jpg",
            "media_shape": "none",
            "title": "Ritu R Shiragannavar",
            "caption": "<p>Front-End Engineer<\/p>",
            "cta_label": "",
            "cta_url": "",
            "target": false,
            "seo_h_tag": "h3"
          }
        },
        "image_paDGgY": {
          "type": "image",
          "settings": {
            "image": "shopify:\/\/shop_images\/gururaj_1.png",
            "media_shape": "none",
            "title": "Gururaj Mannolkar",
            "caption": "<p>Full-Stack Engineer<\/p>",
            "cta_label": "",
            "cta_url": "",
            "target": false,
            "seo_h_tag": "h3"
          }
        },
        "image_HBjg3a": {
          "type": "image",
          "settings": {
            "image": "shopify:\/\/shop_images\/brijesh.png",
            "media_shape": "none",
            "title": "Brijesh M Patil",
            "caption": "<p>Front-End Engineer<\/p>",
            "cta_label": "",
            "cta_url": "",
            "target": false,
            "seo_h_tag": "h3"
          }
        },
        "image_QzCQ7y": {
          "type": "image",
          "settings": {
            "image": "shopify:\/\/shop_images\/Hussain.jpg",
            "media_shape": "none",
            "title": "Saddam Husen",
            "caption": "<p>Office Assistant<\/p>",
            "cta_label": "",
            "cta_url": "",
            "target": false,
            "seo_h_tag": "h3"
          }
        }
      },
      "block_order": [
        "image_KxfFDM",
        "image_mCVe99",
        "image_dK63rr",
        "image_pbe3PX",
        "image_fcebUT",
        "image_9TGVBq",
        "image_Ab8Eix",
        "image_Jii8PU",
        "image_rJtbdm",
        "image_A4YNrX",
        "image_T3Ecmy",
        "image_ReqXVk",
        "image_zLHitx",
        "image_TccPRx",
        "image_awrwUD",
        "image_GWnRe7",
        "image_giECXa",
        "image_kFAFMG",
        "image_DG73Cy",
        "image_8LDRXm",
        "image_gLMdt3",
        "image_hBnaiL",
        "image_JGFAa7",
        "image_qbbcVw",
        "image_h94zNC",
        "image_7mHEQe",
        "image_paDGgY",
        "image_HBjg3a",
        "image_QzCQ7y"
      ],
      "settings": {
        "heading": "Meet our team",
        "cta_label": "",
        "cta_link": "",
        "seo_h_tag": "h2",
        "disable_section_title_border": false,
        "layout_desktop": "grid-4 grid-portable-3 grid-lap-2",
        "style": "grid",
        "image_aspect_ratio": "1",
        "title_text_font": "text-font--body",
        "title_text_size": "text-size--30",
        "title_text_weight": true,
        "subtitle_text_font": "text-font--body",
        "subtitle_text_size": "text-size--18",
        "subtitle_text_line_height": "text-line-height--default",
        "color_scheme": "scheme1",
        "disable_section_bottom_border": false,
        "disable_border": false,
        "remove_border_radius": false,
        "remove_padding": false
      }
    },
    "rich_text_i7mXkN": {
      "type": "rich-text",
      "blocks": {
        "text_pb9Awn": {
          "type": "text",
          "settings": {
            "text": "<p>Are you the pro we're searching for?<\/p>",
            "text_font": "text-font--headings",
            "text_size": "text-size--60",
            "mobile_text_size": "1",
            "text_line_height": "text-line-height--default",
            "seo_h_tag": "span"
          }
        },
        "text_UxMiaU": {
          "type": "text",
          "settings": {
            "text": "<p>We are constantly looking for talent across the board. Feel like you have what it takes To make a difference for our clients.<\/p>",
            "text_font": "text-font--body",
            "text_size": "text-size--20",
            "mobile_text_size": "1",
            "text_line_height": "text-line-height--default",
            "seo_h_tag": "span"
          }
        },
        "button_3KgX7G": {
          "type": "button",
          "settings": {
            "button_label": "View Openings",
            "link": "",
            "target": false,
            "button_style": "solid",
            "button_size": "button--regular",
            "button_hover": "-arrow"
          }
        }
      },
      "block_order": [
        "text_pb9Awn",
        "text_UxMiaU",
        "button_3KgX7G"
      ],
      "settings": {
        "heading": "",
        "seo_h_tag": "h2",
        "disable_section_title_border": false,
        "image_aspect_ratio": "1",
        "image_position": "top no-image",
        "image_position_mobile": "above",
        "image_crop": false,
        "image_overlap": false,
        "image_overlay": "rgba(0,0,0,0)",
        "media_shape": "none",
        "remove_media_border_radius": false,
        "text_alignment": "horizontal-left align-content--vertical-middle",
        "spacing": 24,
        "gutter": "large",
        "width": "50",
        "color_scheme": "scheme4",
        "disable_section_bottom_border": false,
        "color_scheme_card": "scheme4",
        "disable_border": false,
        "remove_border_radius": false,
        "remove_padding": false,
        "add_border": true,
        "hide_block_if": false
      }
    }
  },
  "order": [
    "main",
    "rich_text_jnBDC4",
    "image_xQfN9c",
    "promotion_blocks_mLNkjm",
    "vertical_slider_BxeYTt",
    "promotion_blocks_jTkEbT",
    "video_Mx63EX",
    "promotion_blocks_RcyXUR",
    "promotion_blocks_HCAVU9",
    "text_columns_images_Na86Er",
    "rich_text_i7mXkN"
  ]
}
